messenger_server_app-0.0.2.data/scripts/server_run
server/__init__.py
server/server.py
server/common/__init__.py
server/common/config.py
server/common/decorators.py
server/common/descrptrs.py
server/common/errors.py
server/common/jim.py
server/common/metaclasses.py
server/common/utils.py
server/database/__init__.py
server/database/server_database.py
server/logs/__init__.py
server/logs/config_client_log.py
server/logs/config_server_log.py
server/server/__init__.py
server/server/add_user.py
server/server/config_window.py
server/server/core.py
server/server/main_window.py
server/server/remove_user.py
server/server/stat_window.py
server/unit_tests/__init__.py
server/unit_tests/test_client.py
server/unit_tests/test_server.py
server/unit_tests/test_utils.py
messenger_server_app-0.0.2.dist-info/METADATA
messenger_server_app-0.0.2.dist-info/WHEEL
messenger_server_app-0.0.2.dist-info/top_level.txt
messenger_server_app-0.0.2.dist-info/RECORD
