Metadata-Version: 2.1
Name: messenger-server-app
Version: 0.0.2
Summary: Messenger Server
Home-page: UNKNOWN
Author: Minor Anatolii
Author-email: anminor91@gmail.com
License: UNKNOWN
Platform: UNKNOWN
Requires-Dist: PyQt5
Requires-Dist: pycryptodome
Requires-Dist: pycryptodomex
Requires-Dist: sqlalchemy
